{
    "b95b9b901ef8e98b": {
        "user": "developer",
        "password": "AstIdi2023"
    },
    "898e97efba7d1029": {},
    "ee258853e6e88ba5": {},
    "e1c8d5099fad94ac": {
        "username": "developer "
    },
    "93cbcac54148d5b4": {},
    "ed9b221581eda3eb": {
        "username": "developer",
        "password": "AstIdi2023"
    },
    "e64ddd1601c94a57": {
        "username": "developer"
    },
    "f07312bfad57c2f1": {
        "username": "developer"
    },
    "6d18319cea4c3fb6": {
        "username": "developer"
    },
    "0c04a3d38b0e7fb4": {},
    "31be8b5fe1fca7e6": {
        "user": "cristianhu",
        "password": "060221"
    },
    "404ae85f93f286a9": {
        "user": "cristianhu",
        "password": "060221"
    },
    "0f11cda57c373152": {},
    "da0b6f42.c66398": {}
}